apodo/__init__.py
apodo/request.py
apodo/response.py
apodo/server.py
apodo-0.1.0.dev0.dist-info/WHEEL
apodo-0.1.0.dev0.dist-info/METADATA
apodo-0.1.0.dev0.dist-info/RECORD
