Metadata-Version: 2.1
Name: apodo
Version: 0.1.0.dev0
Summary: A remarkably fast asynchronous web framework for Python.
Author: Elliott Maguire
Author-email: me@elliott-m.com
Requires-Python: >=3.7,<4.0
Classifier: Programming Language :: Python :: 3
Classifier: Programming Language :: Python :: 3.7
Requires-Dist: cython (>=0.29.12,<0.30.0)
